Workbook

Sheet employees
A1: employee_id | B1: employee_name | C1: department | D1: monthly_salary_usd | E1: hourly_rate
A2: E001 | B2: Amina Rahman | C2: Engineering | D2: 1800 | E2: 11.25
A3: E002 | B3: Tanvir Hasan | C3: Engineering | D3: 1500 | E3: 9.375
A4: E003 | B4: Nadia Islam | C4: Design | D4: 1300 | E4: 8.125
A5: E004 | B5: Rakib Ahmed | C5: Engineering | D5: 1600 | E5: 10
A6: E005 | B6: Farhana Akter | C6: QA | D6: 1200 | E6: 7.5
A7: E006 | B7: Sajid Karim | C7: Engineering | D7: 1700 | E7: 10.625
A8: E007 | B8: Mehedi Chowdhury | C8: Project Management | D8: 1900 | E8: 11.875
A9: E008 | B9: Jannat Sultana | C9: QA | D9: 1250 | E9: 7.8125

Sheet projects
A1: project_id | B1: project_name | C1: client | D1: monthly_revenue_usd | E1: project_status
A2: P101 | B2: Briclab | C2: Northstar Ltd | D2: 12000 | E2: Active
A3: P102 | B3: FinTrack | C3: Delta Finance | D3: 9500 | E3: Active
A4: P103 | B4: ShopEase | C4: RetailWorks | D4: 8000 | E4: Active
A5: P104 | B5: MediCore | C5: HealthBridge | D5: 11000 | E5: Active
A6: P105 | B6: LearnLoop | C6: EduSpark | D6: 7000 | E6: Active

Sheet expenses
A1: expense_id | B1: expense_date | C1: project_id | D1: expense_category | E1: amount_usd
A2: EX001 | C2: P101 | D2: Cloud hosting | E2: 420
A3: EX006 | C3: P101 | D3: Software subscription | E3: 450
A4: EX011 | C4: P101 | D4: Cloud hosting | E4: 470
A5: EX002 | C5: P102 | D5: Software subscription | E5: 250
A6: EX007 | C6: P102 | D6: Cloud hosting | E6: 270
A7: EX012 | C7: P102 | D7: Software subscription | E7: 290
A8: EX003 | C8: P103 | D8: Cloud hosting | E8: 310
A9: EX008 | C9: P103 | D9: Software subscription | E9: 330
A10: EX013 | C10: P103 | D10: Cloud hosting | E10: 350
A11: EX004 | C11: P104 | D11: Software subscription | E11: 480
A12: EX009 | C12: P104 | D12: Cloud hosting | E12: 510
A13: EX014 | C13: P104 | D13: Software subscription | E13: 530
... A16: EX015 | C16: P105 | D16: Cloud hosting | E16: 240

Sheet timesheets
A1: timesheet_id | B1: work_date | C1: employee_id | D1: project_id | E1: hours_worked | F1: approval_status | G1: employee_name | H1: hourly_rate | I1: labor_cost | J1: month
A2: TS001 | B2: 46205 | C2: E001 | D2: P101 | E2: 120 | F2: Approved | G2: =_xlfn.XLOOKUP(timesheets[[#This Row],[employee_id]],employees[employee_id],employees[employee_name]) -> Amina Rahman | H2: =_xlfn.XLOOKUP(timesheets[[#This Row],[employee_id]],employees[employee_id],employees[hourly_rate]) -> 11.25 | I2: =timesheets[[#This Row],[hourly_rate]]*timesheets[[#This Row],[hours_worked]] -> 1350 | J2: =timesheets[[#This Row],[work_date]] -> 46205
A3: TS002 | B3: 46208 | C3: E002 | D3: P101 | E3: 100 | F3: Approved | G3: =_xlfn.XLOOKUP(timesheets[[#This Row],[employee_id]],employees[employee_id],employees[employee_name]) -> Tanvir Hasan | H3: =_xlfn.XLOOKUP(timesheets[[#This Row],[employee_id]],employees[employee_id],employees[hourly_rate]) -> 9.375 | I3: =timesheets[[#This Row],[hourly_rate]]*timesheets[[#This Row],[hours_worked]] -> 937.5 | J3: =timesheets[[#This Row],[work_date]] -> 46208
A4: TS011 | B4: 46236 | C4: E001 | D4: P101 | E4: 125 | F4: Approved | G4: =_xlfn.XLOOKUP(timesheets[[#This Row],[employee_id]],employees[employee_id],employees[employee_name]) -> Amina Rahman | H4: =_xlfn.XLOOKUP(timesheets[[#This Row],[employee_id]],employees[employee_id],employees[hourly_rate]) -> 11.25 | I4: =timesheets[[#This Row],[hourly_rate]]*timesheets[[#This Row],[hours_worked]] -> 1406.25 | J4: =timesheets[[#This Row],[work_date]] -> 46236
A5: TS012 | B5: 46238 | C5: E002 | D5: P101 | E5: 105 | F5: Approved | G5: =_xlfn.XLOOKUP(timesheets[[#This Row],[employee_id]],employees[employee_id],employees[employee_name]) -> Tanvir Hasan | H5: =_xlfn.XLOOKUP(timesheets[[#This Row],[employee_id]],employees[employee_id],employees[hourly_rate]) -> 9.375 | I5: =timesheets[[#This Row],[hourly_rate]]*timesheets[[#This Row],[hours_worked]] -> 984.375 | J5: =timesheets[[#This Row],[work_date]] -> 46238
A6: TS021 | B6: 46267 | C6: E001 | D6: P101 | E6: 130 | F6: Approved | G6: =_xlfn.XLOOKUP(timesheets[[#This Row],[employee_id]],employees[employee_id],employees[employee_name]) -> Amina Rahman | H6: =_xlfn.XLOOKUP(timesheets[[#This Row],[employee_id]],employees[employee_id],employees[hourly_rate]) -> 11.25 | I6: =timesheets[[#This Row],[hourly_rate]]*timesheets[[#This Row],[hours_worked]] -> 1462.5 | J6: =timesheets[[#This Row],[work_date]] -> 46267
A7: TS022 | B7: 46269 | C7: E002 | D7: P101 | E7: 110 | F7: Approved | G7: =_xlfn.XLOOKUP(timesheets[[#This Row],[employee_id]],employees[employee_id],employees[employee_name]) -> Tanvir Hasan | H7: =_xlfn.XLOOKUP(timesheets[[#This Row],[employee_id]],employees[employee_id],employees[hourly_rate]) -> 9.375 | I7: =timesheets[[#This Row],[hourly_rate]]*timesheets[[#This Row],[hours_worked]] -> 1031.25 | J7: =timesheets[[#This Row],[work_date]] -> 46269
A8: TS003 | B8: 46211 | C8: E003 | D8: P102 | E8: 90 | F8: Approved | G8: =_xlfn.XLOOKUP(timesheets[[#This Row],[employee_id]],employees[employee_id],employees[employee_name]) -> Nadia Islam | H8: =_xlfn.XLOOKUP(timesheets[[#This Row],[employee_id]],employees[employee_id],employees[hourly_rate]) -> 8.125 | I8: =timesheets[[#This Row],[hourly_rate]]*timesheets[[#This Row],[hours_worked]] -> 731.25 | J8: =timesheets[[#This Row],[work_date]] -> 46211
A9: TS004 | B9: 46213 | C9: E004 | D9: P102 | E9: 110 | F9: Approved | G9: =_xlfn.XLOOKUP(timesheets[[#This Row],[employee_id]],employees[employee_id],employees[employee_name]) -> Rakib Ahmed | H9: =_xlfn.XLOOKUP(timesheets[[#This Row],[employee_id]],employees[employee_id],employees[hourly_rate]) -> 10 | I9: =timesheets[[#This Row],[hourly_rate]]*timesheets[[#This Row],[hours_worked]] -> 1100 | J9: =timesheets[[#This Row],[work_date]] -> 46213
A10: TS013 | B10: 46240 | C10: E003 | D10: P102 | E10: 95 | F10: Approved | G10: =_xlfn.XLOOKUP(timesheets[[#This Row],[employee_id]],employees[employee_id],employees[employee_name]) -> Nadia Islam | H10: =_xlfn.XLOOKUP(timesheets[[#This Row],[employee_id]],employees[employee_id],employees[hourly_rate]) -> 8.125 | I10: =timesheets[[#This Row],[hourly_rate]]*timesheets[[#This Row],[hours_worked]] -> 771.875 | J10: =timesheets[[#This Row],[work_date]] -> 46240
A11: TS014 | B11: 46242 | C11: E004 | D11: P102 | E11: 115 | F11: Approved | G11: =_xlfn.XLOOKUP(timesheets[[#This Row],[employee_id]],employees[employee_id],employees[employee_name]) -> Rakib Ahmed | H11: =_xlfn.XLOOKUP(timesheets[[#This Row],[employee_id]],employees[employee_id],employees[hourly_rate]) -> 10 | I11: =timesheets[[#This Row],[hourly_rate]]*timesheets[[#This Row],[hours_worked]] -> 1150 | J11: =timesheets[[#This Row],[work_date]] -> 46242
A12: TS023 | B12: 46271 | C12: E003 | D12: P102 | E12: 100 | F12: Approved | G12: =_xlfn.XLOOKUP(timesheets[[#This Row],[employee_id]],employees[employee_id],employees[employee_name]) -> Nadia Islam | H12: =_xlfn.XLOOKUP(timesheets[[#This Row],[employee_id]],employees[employee_id],employees[hourly_rate]) -> 8.125 | I12: =timesheets[[#This Row],[hourly_rate]]*timesheets[[#This Row],[hours_worked]] -> 812.5 | J12: =timesheets[[#This Row],[work_date]] -> 46271
A13: TS024 | B13: 46273 | C13: E004 | D13: P102 | E13: 120 | F13: Approved | G13: =_xlfn.XLOOKUP(timesheets[[#This Row],[employee_id]],employees[employee_id],employees[employee_name]) -> Rakib Ahmed | H13: =_xlfn.XLOOKUP(timesheets[[#This Row],[employee_id]],employees[employee_id],employees[hourly_rate]) -> 10 | I13: =timesheets[[#This Row],[hourly_rate]]*timesheets[[#This Row],[hours_worked]] -> 1200 | J13: =timesheets[[#This Row],[work_date]] -> 46273
... A31: TS030 | B31: 46285 | C31: E002 | D31: P105 | E31: 100 | F31: Approved | G31: =_xlfn.XLOOKUP(timesheets[[#This Row],[employee_id]],employees[employee_id],employees[employee_name]) -> Tanvir Hasan | H31: =_xlfn.XLOOKUP(timesheets[[#This Row],[employee_id]],employees[employee_id],employees[hourly_rate]) -> 9.375 | I31: =timesheets[[#This Row],[hourly_rate]]*timesheets[[#This Row],[hours_worked]] -> 937.5 | J31: =timesheets[[#This Row],[work_date]] -> 46285

Sheet Project P&L
A1: Project_id | B1: project_name | C1: Revenue 3 month | D1: hours | E1: labor_cost | F1: other_cost | G1: total_cost | H1: profit | I1: margin | J1: Profit per Hour | K1: per Houe %
A2: P101 | B2: =_xlfn.XLOOKUP(A2,projects[project_id],projects[project_name]) -> Briclab | C2: =_xlfn.XLOOKUP('Project P&L'!A2,projects[project_id],projects[monthly_revenue_usd])*3 -> 36000 | D2: =SUMIFS(timesheets[hours_worked],timesheets[project_id],'Project P&L'!A2) -> 690 | E2: =SUMIFS(timesheets[labor_cost],timesheets[project_id],'Project P&L'!A2) -> 7171.875 | F2: =SUMIFS(expenses[amount_usd],expenses[project_id],'Project P&L'!A2) -> 1340 | G2: =E2+F2 -> 8511.875 | H2: =C2-G2 -> 27488.125 | I2: =H2/C2 -> 0.76355903 | J2: =H2/D2 -> 39.837862 | K2: =J2/SUM($J$2:$J$6) -> 0.23816988
A3: P102 | B3: =_xlfn.XLOOKUP(A3,projects[project_id],projects[project_name]) -> FinTrack | C3: =_xlfn.XLOOKUP('Project P&L'!A3,projects[project_id],projects[monthly_revenue_usd])*3 -> 28500 | D3: =SUMIFS(timesheets[hours_worked],timesheets[project_id],'Project P&L'!A3) -> 630 | E3: =SUMIFS(timesheets[labor_cost],timesheets[project_id],'Project P&L'!A3) -> 5765.625 | F3: =SUMIFS(expenses[amount_usd],expenses[project_id],'Project P&L'!A3) -> 810 | G3: =E3+F3 -> 6575.625 | H3: =C3-G3 -> 21924.375 | I3: =H3/C3 -> 0.76927632 | J3: =H3/D3 -> 34.800595 | K3: =J3/SUM($J$2:$J$6) -> 0.20805468
A4: P103 | B4: =_xlfn.XLOOKUP(A4,projects[project_id],projects[project_name]) -> ShopEase | C4: =_xlfn.XLOOKUP('Project P&L'!A4,projects[project_id],projects[monthly_revenue_usd])*3 -> 24000 | D4: =SUMIFS(timesheets[hours_worked],timesheets[project_id],'Project P&L'!A4) -> 720 | E4: =SUMIFS(timesheets[labor_cost],timesheets[project_id],'Project P&L'!A4) -> 6665.625 | F4: =SUMIFS(expenses[amount_usd],expenses[project_id],'Project P&L'!A4) -> 990 | G4: =E4+F4 -> 7655.625 | H4: =C4-G4 -> 16344.375 | I4: =H4/C4 -> 0.68101563 | J4: =H4/D4 -> 22.700521 | K4: =J4/SUM($J$2:$J$6) -> 0.13571462
A5: P104 | B5: =_xlfn.XLOOKUP(A5,projects[project_id],projects[project_name]) -> MediCore | C5: =_xlfn.XLOOKUP('Project P&L'!A5,projects[project_id],projects[monthly_revenue_usd])*3 -> 33000 | D5: =SUMIFS(timesheets[hours_worked],timesheets[project_id],'Project P&L'!A5) -> 600 | E5: =SUMIFS(timesheets[labor_cost],timesheets[project_id],'Project P&L'!A5) -> 5967.1875 | F5: =SUMIFS(expenses[amount_usd],expenses[project_id],'Project P&L'!A5) -> 1520 | G5: =E5+F5 -> 7487.1875 | H5: =C5-G5 -> 25512.812 | I5: =H5/C5 -> 0.77311553 | J5: =H5/D5 -> 42.521354 | K5: =J5/SUM($J$2:$J$6) -> 0.25421309
A6: P105 | B6: =_xlfn.XLOOKUP(A6,projects[project_id],projects[project_name]) -> LearnLoop | C6: =_xlfn.XLOOKUP('Project P&L'!A6,projects[project_id],projects[monthly_revenue_usd])*3 -> 21000 | D6: =SUMIFS(timesheets[hours_worked],timesheets[project_id],'Project P&L'!A6) -> 540 | E6: =SUMIFS(timesheets[labor_cost],timesheets[project_id],'Project P&L'!A6) -> 5540.625 | F6: =SUMIFS(expenses[amount_usd],expenses[project_id],'Project P&L'!A6) -> 660 | G6: =E6+F6 -> 6200.625 | H6: =C6-G6 -> 14799.375 | I6: =H6/C6 -> 0.70473214 | J6: =H6/D6 -> 27.40625 | K6: =J6/SUM($J$2:$J$6) -> 0.16384773
B8: Total | C8: =SUM(C2:C7) -> 142500 | D8: =SUM(D2:D7) -> 3180 | E8: =SUM(E2:E7) -> 31110.938 | F8: =SUM(F2:F7) -> 5320 | G8: =SUM(G2:G7) -> 36430.938 | H8: =SUM(H2:H7) -> 106069.06

Sheet Utilization Employee
A3: Sum of hours_worked | B3: Column Labels
B4: Jul | C4: Aug | D4: Sep | E4: Grand Total
A5: Row Labels | H5: Employee | I5: Total Work | J5: Utilization
A6: E001 | B6: 200 | C6: 210 | D6: 220 | E6: 630 | H6: =_xlfn.XLOOKUP(A6,employees[employee_id],employees[employee_name]) -> Amina Rahman | I6: =SUMIFS(timesheets[hours_worked],timesheets[employee_id],'Utilization Employee'!A6) -> 630 | J6: =I6/480 -> 1.3125
A7: E002 | B7: 190 | C7: 200 | D7: 210 | E7: 600 | H7: =_xlfn.XLOOKUP(A7,employees[employee_id],employees[employee_name]) -> Tanvir Hasan | I7: =SUMIFS(timesheets[hours_worked],timesheets[employee_id],'Utilization Employee'!A7) -> 600 | J7: =I7/480 -> 1.25
A8: E003 | B8: 90 | C8: 95 | D8: 100 | E8: 285 | H8: =_xlfn.XLOOKUP(A8,employees[employee_id],employees[employee_name]) -> Nadia Islam | I8: =SUMIFS(timesheets[hours_worked],timesheets[employee_id],'Utilization Employee'!A8) -> 285 | J8: =I8/480 -> 0.59375
A9: E004 | B9: 110 | C9: 115 | D9: 120 | E9: 345 | H9: =_xlfn.XLOOKUP(A9,employees[employee_id],employees[employee_name]) -> Rakib Ahmed | I9: =SUMIFS(timesheets[hours_worked],timesheets[employee_id],'Utilization Employee'!A9) -> 345 | J9: =I9/480 -> 0.71875
A10: E005 | B10: 100 | C10: 105 | D10: 110 | E10: 315 | H10: =_xlfn.XLOOKUP(A10,employees[employee_id],employees[employee_name]) -> Farhana Akter | I10: =SUMIFS(timesheets[hours_worked],timesheets[employee_id],'Utilization Employee'!A10) -> 315 | J10: =I10/480 -> 0.65625
A11: E006 | B11: 130 | C11: 135 | D11: 140 | E11: 405 | H11: =_xlfn.XLOOKUP(A11,employees[employee_id],employees[employee_name]) -> Sajid Karim | I11: =SUMIFS(timesheets[hours_worked],timesheets[employee_id],'Utilization Employee'!A11) -> 405 | J11: =I11/480 -> 0.84375
A12: E007 | B12: 100 | C12: 105 | D12: 110 | E12: 315 | H12: =_xlfn.XLOOKUP(A12,employees[employee_id],employees[employee_name]) -> Mehedi Chowdhury | I12: =SUMIFS(timesheets[hours_worked],timesheets[employee_id],'Utilization Employee'!A12) -> 315 | J12: =I12/480 -> 0.65625
A13: E008 | B13: 90 | C13: 95 | D13: 100 | E13: 285 | H13: =_xlfn.XLOOKUP(A13,employees[employee_id],employees[employee_name]) -> Jannat Sultana | I13: =SUMIFS(timesheets[hours_worked],timesheets[employee_id],'Utilization Employee'!A13) -> 285 | J13: =I13/480 -> 0.59375
A14: Grand Total | B14: 1010 | C14: 1060 | D14: 1110 | E14: 3180 | I14: =SUM(I6:I13) -> 3180

Sheet charts
