Workbook

Sheet employees
A1: employee_id | B1: employee_name | C1: department | D1: monthly_salary_usd | E1: Per hour
A2: E001 | B2: Amina Rahman | C2: Engineering | D2: 1800 | E2: =D2/160 -> 11.25
A3: E002 | B3: Tanvir Hasan | C3: Engineering | D3: 1500 | E3: =D3/160 -> 9.375
A4: E003 | B4: Nadia Islam | C4: Design | D4: 1300 | E4: =D4/160 -> 8.125
A5: E004 | B5: Rakib Ahmed | C5: Engineering | D5: 1600 | E5: =D5/160 -> 10
A6: E005 | B6: Farhana Akter | C6: QA | D6: 1200 | E6: =D6/160 -> 7.5
A7: E006 | B7: Sajid Karim | C7: Engineering | D7: 1700 | E7: =D7/160 -> 10.625
A8: E007 | B8: Mehedi Chowdhury | C8: Project Management | D8: 1900 | E8: =D8/160 -> 11.875
A9: E008 | B9: Jannat Sultana | C9: QA | D9: 1250 | E9: =D9/160 -> 7.8125
D12: =SUM(D2:D11) -> 12250

Sheet projects
A1: project_id | B1: project_name | C1: client | D1: monthly_revenue_usd | E1: project_status
A2: P101 | B2: Briclab | C2: Northstar Ltd | D2: 12000 | E2: Active
A3: P102 | B3: FinTrack | C3: Delta Finance | D3: 9500 | E3: Active
A4: P103 | B4: ShopEase | C4: RetailWorks | D4: 8000 | E4: Active
A5: P104 | B5: MediCore | C5: HealthBridge | D5: 11000 | E5: Active
A6: P105 | B6: LearnLoop | C6: EduSpark | D6: 7000 | E6: Active
D8: =SUM(D2:D7) -> 47500

Sheet timesheets
A1: timesheet_id | B1: work_date | C1: employee_id | D1: Employee | E1: project_id | F1: project | G1: hours_worked | H1: approval_status
A2: TS001 | B2: 2026-07-02 | C2: E001 | D2: =_xlfn.XLOOKUP(C2,employees!$A$2:$A$9,employees!$B$2:$B$9) -> Amina Rahman | E2: P101 | F2: =_xlfn.XLOOKUP(E2,projects!$A$2:$A$6,projects!$B$2:$B$6) -> Briclab | G2: 120 | H2: Approved
A3: TS002 | B3: 2026-07-05 | C3: E002 | D3: =_xlfn.XLOOKUP(C3,employees!$A$2:$A$9,employees!$B$2:$B$9) -> Tanvir Hasan | E3: P101 | F3: =_xlfn.XLOOKUP(E3,projects!$A$2:$A$6,projects!$B$2:$B$6) -> Briclab | G3: 100 | H3: Approved
A4: TS011 | B4: 2026-08-02 | C4: E001 | D4: =_xlfn.XLOOKUP(C4,employees!$A$2:$A$9,employees!$B$2:$B$9) -> Amina Rahman | E4: P101 | F4: =_xlfn.XLOOKUP(E4,projects!$A$2:$A$6,projects!$B$2:$B$6) -> Briclab | G4: 125 | H4: Approved
A5: TS012 | B5: 2026-08-04 | C5: E002 | D5: =_xlfn.XLOOKUP(C5,employees!$A$2:$A$9,employees!$B$2:$B$9) -> Tanvir Hasan | E5: P101 | F5: =_xlfn.XLOOKUP(E5,projects!$A$2:$A$6,projects!$B$2:$B$6) -> Briclab | G5: 105 | H5: Approved
A6: TS021 | B6: 2026-09-02 | C6: E001 | D6: =_xlfn.XLOOKUP(C6,employees!$A$2:$A$9,employees!$B$2:$B$9) -> Amina Rahman | E6: P101 | F6: =_xlfn.XLOOKUP(E6,projects!$A$2:$A$6,projects!$B$2:$B$6) -> Briclab | G6: 130 | H6: Approved
A7: TS022 | B7: 2026-09-04 | C7: E002 | D7: =_xlfn.XLOOKUP(C7,employees!$A$2:$A$9,employees!$B$2:$B$9) -> Tanvir Hasan | E7: P101 | F7: =_xlfn.XLOOKUP(E7,projects!$A$2:$A$6,projects!$B$2:$B$6) -> Briclab | G7: 110 | H7: Approved
A8: TS003 | B8: 2026-07-08 | C8: E003 | D8: =_xlfn.XLOOKUP(C8,employees!$A$2:$A$9,employees!$B$2:$B$9) -> Nadia Islam | E8: P102 | F8: =_xlfn.XLOOKUP(E8,projects!$A$2:$A$6,projects!$B$2:$B$6) -> FinTrack | G8: 90 | H8: Approved
A9: TS004 | B9: 2026-07-10 | C9: E004 | D9: =_xlfn.XLOOKUP(C9,employees!$A$2:$A$9,employees!$B$2:$B$9) -> Rakib Ahmed | E9: P102 | F9: =_xlfn.XLOOKUP(E9,projects!$A$2:$A$6,projects!$B$2:$B$6) -> FinTrack | G9: 110 | H9: Approved
A10: TS013 | B10: 2026-08-06 | C10: E003 | D10: =_xlfn.XLOOKUP(C10,employees!$A$2:$A$9,employees!$B$2:$B$9) -> Nadia Islam | E10: P102 | F10: =_xlfn.XLOOKUP(E10,projects!$A$2:$A$6,projects!$B$2:$B$6) -> FinTrack | G10: 95 | H10: Approved
A11: TS014 | B11: 2026-08-08 | C11: E004 | D11: =_xlfn.XLOOKUP(C11,employees!$A$2:$A$9,employees!$B$2:$B$9) -> Rakib Ahmed | E11: P102 | F11: =_xlfn.XLOOKUP(E11,projects!$A$2:$A$6,projects!$B$2:$B$6) -> FinTrack | G11: 115 | H11: Approved
A12: TS023 | B12: 2026-09-06 | C12: E003 | D12: =_xlfn.XLOOKUP(C12,employees!$A$2:$A$9,employees!$B$2:$B$9) -> Nadia Islam | E12: P102 | F12: =_xlfn.XLOOKUP(E12,projects!$A$2:$A$6,projects!$B$2:$B$6) -> FinTrack | G12: 100 | H12: Approved
A13: TS024 | B13: 2026-09-08 | C13: E004 | D13: =_xlfn.XLOOKUP(C13,employees!$A$2:$A$9,employees!$B$2:$B$9) -> Rakib Ahmed | E13: P102 | F13: =_xlfn.XLOOKUP(E13,projects!$A$2:$A$6,projects!$B$2:$B$6) -> FinTrack | G13: 120 | H13: Approved
... A22: TS034 | B22: 2026-09-25 | C22: E888 | D22: =_xlfn.XLOOKUP(C22,employees!$A$2:$A$9,employees!$B$2:$B$9) -> #N/A | E22: P103 | F22: =_xlfn.XLOOKUP(E22,projects!$A$2:$A$6,projects!$B$2:$B$6) -> ShopEase | G22: 8 | H22: Pending
A23: TS035 | B23: 2026-09-26 | C23: E005 | D23: =_xlfn.XLOOKUP(C23,employees!$A$2:$A$9,employees!$B$2:$B$9) -> Farhana Akter | E23: P103 | F23: =_xlfn.XLOOKUP(E23,projects!$A$2:$A$6,projects!$B$2:$B$6) -> ShopEase | H23: Approved
A24: TS007 | B24: 2026-07-16 | C24: E007 | D24: =_xlfn.XLOOKUP(C24,employees!$A$2:$A$9,employees!$B$2:$B$9) -> Mehedi Chowdhury | E24: P104 | F24: =_xlfn.XLOOKUP(E24,projects!$A$2:$A$6,projects!$B$2:$B$6) -> MediCore | G24: 100 | H24: Approved
A25: TS008 | B25: 2026-07-18 | C25: E008 | D25: =_xlfn.XLOOKUP(C25,employees!$A$2:$A$9,employees!$B$2:$B$9) -> Jannat Sultana | E25: P104 | F25: =_xlfn.XLOOKUP(E25,projects!$A$2:$A$6,projects!$B$2:$B$6) -> MediCore | G25: 90 | H25: Approved
A26: TS017 | B26: 2026-08-14 | C26: E007 | D26: =_xlfn.XLOOKUP(C26,employees!$A$2:$A$9,employees!$B$2:$B$9) -> Mehedi Chowdhury | E26: P104 | F26: =_xlfn.XLOOKUP(E26,projects!$A$2:$A$6,projects!$B$2:$B$6) -> MediCore | G26: 105 | H26: Approved
A27: TS018 | B27: 2026-08-16 | C27: E008 | D27: =_xlfn.XLOOKUP(C27,employees!$A$2:$A$9,employees!$B$2:$B$9) -> Jannat Sultana | E27: P104 | F27: =_xlfn.XLOOKUP(E27,projects!$A$2:$A$6,projects!$B$2:$B$6) -> MediCore | G27: 95 | H27: Approved
A28: TS027 | B28: 2026-09-14 | C28: E007 | D28: =_xlfn.XLOOKUP(C28,employees!$A$2:$A$9,employees!$B$2:$B$9) -> Mehedi Chowdhury | E28: P104 | F28: =_xlfn.XLOOKUP(E28,projects!$A$2:$A$6,projects!$B$2:$B$6) -> MediCore | G28: 110 | H28: Approved
A29: TS028 | B29: 2026-09-16 | C29: E008 | D29: =_xlfn.XLOOKUP(C29,employees!$A$2:$A$9,employees!$B$2:$B$9) -> Jannat Sultana | E29: P104 | F29: =_xlfn.XLOOKUP(E29,projects!$A$2:$A$6,projects!$B$2:$B$6) -> MediCore | G29: 100 | H29: Approved
A30: TS009 | B30: 2026-07-20 | C30: E001 | D30: =_xlfn.XLOOKUP(C30,employees!$A$2:$A$9,employees!$B$2:$B$9) -> Amina Rahman | E30: P105 | F30: =_xlfn.XLOOKUP(E30,projects!$A$2:$A$6,projects!$B$2:$B$6) -> LearnLoop | G30: 80 | H30: Approved
A31: TS010 | B31: 2026-07-22 | C31: E002 | D31: =_xlfn.XLOOKUP(C31,employees!$A$2:$A$9,employees!$B$2:$B$9) -> Tanvir Hasan | E31: P105 | F31: =_xlfn.XLOOKUP(E31,projects!$A$2:$A$6,projects!$B$2:$B$6) -> LearnLoop | G31: 90 | H31: Approved
A32: TS019 | B32: 2026-08-18 | C32: E001 | D32: =_xlfn.XLOOKUP(C32,employees!$A$2:$A$9,employees!$B$2:$B$9) -> Amina Rahman | E32: P105 | F32: =_xlfn.XLOOKUP(E32,projects!$A$2:$A$6,projects!$B$2:$B$6) -> LearnLoop | G32: 85 | H32: Approved
A33: TS020 | B33: 2026-08-20 | C33: E002 | D33: =_xlfn.XLOOKUP(C33,employees!$A$2:$A$9,employees!$B$2:$B$9) -> Tanvir Hasan | E33: P105 | F33: =_xlfn.XLOOKUP(E33,projects!$A$2:$A$6,projects!$B$2:$B$6) -> LearnLoop | G33: 95 | H33: Approved
A34: TS029 | B34: 2026-09-18 | C34: E001 | D34: =_xlfn.XLOOKUP(C34,employees!$A$2:$A$9,employees!$B$2:$B$9) -> Amina Rahman | E34: P105 | F34: =_xlfn.XLOOKUP(E34,projects!$A$2:$A$6,projects!$B$2:$B$6) -> LearnLoop | G34: 90 | H34: Approved
A35: TS030 | B35: 2026-09-20 | C35: E002 | D35: =_xlfn.XLOOKUP(C35,employees!$A$2:$A$9,employees!$B$2:$B$9) -> Tanvir Hasan | E35: P105 | F35: =_xlfn.XLOOKUP(E35,projects!$A$2:$A$6,projects!$B$2:$B$6) -> LearnLoop | G35: 100 | H35: Approved
A36: TS031 | B36: 2026-09-22 | C36: E003 | D36: =_xlfn.XLOOKUP(C36,employees!$A$2:$A$9,employees!$B$2:$B$9) -> Nadia Islam | E36: P999 | F36: =_xlfn.XLOOKUP(E36,projects!$A$2:$A$6,projects!$B$2:$B$6) -> #N/A | G36: 12 | H36: approved
G38: =SUBTOTAL(9,G2:G36) -> 3190

Sheet expenses
A1: expense_id | B1: expense_date | C1: project_id | D1: Project | E1: expense_category | F1: amount_usd | G1: currency
A2: EX001 | B2: 2026-07-03 | C2: P101 | D2: =_xlfn.XLOOKUP(C2,projects!$A$2:$A$6,projects!$B$2:$B$6) -> Briclab | E2: Cloud hosting | F2: 420 | G2: USD
A3: EX006 | B3: 2026-08-03 | C3: P101 | D3: =_xlfn.XLOOKUP(C3,projects!$A$2:$A$6,projects!$B$2:$B$6) -> Briclab | E3: Software subscription | F3: 450 | G3: USD
A4: EX011 | B4: 2026-09-03 | C4: P101 | D4: =_xlfn.XLOOKUP(C4,projects!$A$2:$A$6,projects!$B$2:$B$6) -> Briclab | E4: Cloud hosting | F4: 470 | G4: USD
A5: EX002 | B5: 2026-07-08 | C5: P102 | D5: =_xlfn.XLOOKUP(C5,projects!$A$2:$A$6,projects!$B$2:$B$6) -> FinTrack | E5: Software subscription | F5: 250 | G5: USD
A6: EX007 | B6: 2026-08-08 | C6: P102 | D6: =_xlfn.XLOOKUP(C6,projects!$A$2:$A$6,projects!$B$2:$B$6) -> FinTrack | E6: Cloud hosting | F6: 270 | G6: USD
A7: EX012 | B7: 2026-09-08 | C7: P102 | D7: =_xlfn.XLOOKUP(C7,projects!$A$2:$A$6,projects!$B$2:$B$6) -> FinTrack | E7: Software subscription | F7: 290 | G7: USD
A8: EX003 | B8: 2026-07-11 | C8: P103 | D8: =_xlfn.XLOOKUP(C8,projects!$A$2:$A$6,projects!$B$2:$B$6) -> ShopEase | E8: Cloud hosting | F8: 310 | G8: USD
A9: EX008 | B9: 2026-08-11 | C9: P103 | D9: =_xlfn.XLOOKUP(C9,projects!$A$2:$A$6,projects!$B$2:$B$6) -> ShopEase | E9: Software subscription | F9: 330 | G9: USD
A10: EX013 | B10: 2026-09-11 | C10: P103 | D10: =_xlfn.XLOOKUP(C10,projects!$A$2:$A$6,projects!$B$2:$B$6) -> ShopEase | E10: Cloud hosting | F10: 350 | G10: USD
A11: EX004 | B11: 2026-07-16 | C11: P104 | D11: =_xlfn.XLOOKUP(C11,projects!$A$2:$A$6,projects!$B$2:$B$6) -> MediCore | E11: Software subscription | F11: 480 | G11: USD
A12: EX009 | B12: 2026-08-16 | C12: P104 | D12: =_xlfn.XLOOKUP(C12,projects!$A$2:$A$6,projects!$B$2:$B$6) -> MediCore | E12: Cloud hosting | F12: 510 | G12: USD
A13: EX014 | B13: 2026-09-16 | C13: P104 | D13: =_xlfn.XLOOKUP(C13,projects!$A$2:$A$6,projects!$B$2:$B$6) -> MediCore | E13: Software subscription | F13: 530 | G13: USD
... A17: EX016 | B17: 2026-09-23 | C17: P777 | D17: =_xlfn.XLOOKUP(C17,projects!$A$2:$A$6,projects!$B$2:$B$6) -> #N/A | E17: Software subscription | F17: 95 | G17: USD
F20: =SUBTOTAL(9,F2:F17) -> 5415

Sheet README
A1: Field | B1: Value
A2: Project | B2: Employee & Project Profitability Analysis
A3: Period | B3: July–September 2026
A4: Currency | B4: USD
A5: Important | B5: Fictional practice data. Some records intentionally contain data-quality issues.
A6: Revenue assumption | B6: Project monthly revenue applies in each of the three months; verify this assumption in your report.
A7: Labor cost assumption | B7: For beginner practice, allocate salary cost using hourly salary = monthly salary / 160; allocate cost by hours logged.
A8: Utilization assumption | B8: Use 160 available hours per employee per month for this exercise. Note that timesheet hours may be project hours only.
